pyanten/__init__.py
pyanten/Array/__init__.py
pyanten/Array/amplitudeTaper.py
pyanten/Measurement/__init__.py
pyanten/Measurement/NearField/__init__.py
pyanten/Measurement/NearField/seperationDistance.py
pyanten/Measurement/NearField/Planar/__init__.py
pyanten/Measurement/NearField/Planar/angleOfView.py
pyanten/Measurement/NearField/Planar/samplingParameters.py
pyanten/Measurement/NearField/Planar/samplingSpacing.py
pyanten/Measurement/NearField/Planar/scanLength.py
pyanten/Measurement/NearField/Spherical/__init__.py
pyanten/Measurement/NearField/Spherical/maximumRadiusExtent.py
pyanten/Propagation/__init__.py
pyanten/Propagation/farFieldDistance.py
pyanten/Propagation/lineOfSight.py
pyanten/Propagation/pathLoss.py
pyanten/Propagation/radioHorizon.py
pyanten/Utility/__init__.py
pyanten/Utility/frequencyToWavelength.py
pyanten/Utility/gammaDbToReflectedPowerPercentage.py
pyanten/Utility/gammaDbToSwr.py
pyanten/Utility/gammaToSwr.py
pyanten/Utility/swrToGamma.py
pyanten/Utility/swrToGammaDb.py
pyanten/Utility/wavelengthToFrequency.py
pyanten-0.3.8.dist-info/LICENSE
pyanten-0.3.8.dist-info/METADATA
pyanten-0.3.8.dist-info/WHEEL
pyanten-0.3.8.dist-info/top_level.txt
pyanten-0.3.8.dist-info/RECORD
