Metadata-Version: 2.1
Name: pyanten
Version: 0.3.8
Summary: Antenna Toolkit
Home-page: https://github.com/yigithsyn/pyanten
Author: Hüseyin YİĞİT
Author-email: yigit.hsyn@gmail.com
License: GNU Affero General Public License v3
Platform: Any
Classifier: Development Status :: 3 - Alpha
Classifier: License :: OSI Approved :: GNU Affero General Public License v3
Classifier: Operating System :: OS Independent
Classifier: Programming Language :: Python
Classifier: Programming Language :: Python :: 3
Classifier: Intended Audience :: Science/Research
Classifier: Intended Audience :: Other Audience
Classifier: Topic :: Scientific/Engineering
Classifier: Topic :: Scientific/Engineering :: Mathematics
Classifier: Topic :: Scientific/Engineering :: Physics
Requires-Python: >= 3
License-File: LICENSE
Requires-Dist: scipy>=1.6.0
